setup.py
ssstatic/__init__.py
ssstatic.egg-info/PKG-INFO
ssstatic.egg-info/SOURCES.txt
ssstatic.egg-info/dependency_links.txt
ssstatic.egg-info/entry_points.txt
ssstatic.egg-info/requires.txt
ssstatic.egg-info/top_level.txt