Metadata-Version: 1.0
Name: ssstatic
Version: 0.6
Summary: Push a website assets to S3 with or without prefix cache busting.
Home-page: https://github.com/jokull/ssstatic
Author: Jökull Sólberg Auðunsson
Author-email: jokull@solberg.is
License: See LICENSE.
Platform: UNKNOWN
